flexget/__init__.py
flexget/_version.py
flexget/a.py
flexget/config_schema.py
flexget/db_schema.py
flexget/entry.py
flexget/event.py
flexget/ipc.py
flexget/log.py
flexget/manager.py
flexget/options.py
flexget/plugin.py
flexget/task.py
flexget/task_queue.py
flexget/terminal.py
flexget/tray_icon.py
flexget/webserver.py
flexget/api/__init__.py
flexget/api/app.py
flexget/api/core/__init__.py
flexget/api/core/authentication.py
flexget/api/core/cached.py
flexget/api/core/database.py
flexget/api/core/format_checker.py
flexget/api/core/plugins.py
flexget/api/core/schema.py
flexget/api/core/server.py
flexget/api/core/tasks.py
flexget/api/core/user.py
flexget/api/templates/api_response.html
flexget/api/templates/swagger-ui.html
flexget/components/README.md
flexget/components/__init__.py
flexget/components/archive/__init__.py
flexget/components/archive/archive.py
flexget/components/archive/cli.py
flexget/components/archive/db.py
flexget/components/archives/__init__.py
flexget/components/archives/archives.py
flexget/components/archives/decompress.py
flexget/components/archives/utils.py
flexget/components/backlog/__init__.py
flexget/components/backlog/backlog.py
flexget/components/backlog/cli.py
flexget/components/backlog/db.py
flexget/components/bittorrent/__init__.py
flexget/components/bittorrent/convert_magnet.py
flexget/components/bittorrent/magnet_info_hash.py
flexget/components/bittorrent/private_torrents.py
flexget/components/bittorrent/torrent.py
flexget/components/bittorrent/torrent_alive.py
flexget/components/bittorrent/torrent_files.py
flexget/components/bittorrent/torrent_match.py
flexget/components/bittorrent/torrent_scrub.py
flexget/components/bittorrent/torrent_size.py
flexget/components/bittorrent/trackers.py
flexget/components/emby/__init__.py
flexget/components/emby/api_emby.py
flexget/components/emby/emby_list.py
flexget/components/emby/emby_lookup.py
flexget/components/emby/emby_refresh.py
flexget/components/emby/emby_util.py
flexgettest-3.17.6.dist-info/METADATA
flexgettest-3.17.6.dist-info/WHEEL
flexgettest-3.17.6.dist-info/entry_points.txt
flexgettest-3.17.6.dist-info/licenses/LICENSE
flexgettest-3.17.6.dist-info/RECORD
