Metadata-Version: 2.4
Name: flexgettest
Version: 3.17.6
Dynamic: Requires-Dist
Dynamic: Provides-Extra
Summary: FlexGet is a program aimed to automate downloading or processing content (torrents, podcasts, etc.) from different sources like RSS-feeds, html-pages, various sites and more.
Project-URL: Homepage, https://flexget.com
Project-URL: Issue Tracker, https://github.com/Flexget/Flexget/issues
Project-URL: Repository, https://github.com/Flexget/Flexget
Project-URL: Forum, https://github.com/Flexget/Flexget/discussions
Author-email: Marko Koivusalo <marko.koivusalo@gmail.com>, Chase Sterling <chase.sterling@gmail.com>
License: MIT License
License-File: LICENSE
Classifier: Development Status :: 5 - Production/Stable
Classifier: Intended Audience :: End Users/Desktop
Classifier: License :: OSI Approved :: MIT License
Classifier: Natural Language :: English
Classifier: Operating System :: MacOS
Classifier: Operating System :: Microsoft :: Windows
Classifier: Operating System :: POSIX
Classifier: Operating System :: Unix
Classifier: Programming Language :: Python :: 3 :: Only
Classifier: Programming Language :: Python :: 3.9
Classifier: Programming Language :: Python :: 3.10
Classifier: Programming Language :: Python :: 3.11
Classifier: Programming Language :: Python :: 3.12
Classifier: Programming Language :: Python :: 3.13
Classifier: Topic :: Utilities
Classifier: Typing :: Typed
Requires-Python: >=3.9
Requires-Dist: apscheduler~=3.11
Requires-Dist: beautifulsoup4~=4.12
Requires-Dist: cherrypy~=18.10
Requires-Dist: feedparser~=6.0
Requires-Dist: flask-compress~=1.17
Requires-Dist: flask-cors~=6.0
Requires-Dist: flask-login~=0.6.3
Requires-Dist: flask-restx~=1.3
Requires-Dist: flask~=3.1
Requires-Dist: guessit~=3.8
Requires-Dist: html5lib~=1.1
Requires-Dist: importlib-metadata~=8.5; python_version < '3.10'
Requires-Dist: jinja2~=3.1
Requires-Dist: jsonschema~=4.23
Requires-Dist: loguru~=0.7.3
Requires-Dist: packaging~=25.0
Requires-Dist: pendulum~=3.0
Requires-Dist: psutil~=7.0
Requires-Dist: pynzb~=0.1.0
Requires-Dist: pyparsing~=3.2
Requires-Dist: pyrss2gen~=1.1
Requires-Dist: python-dateutil~=2.9
Requires-Dist: pyyaml~=6.0
Requires-Dist: rebulk~=3.2
Requires-Dist: requests~=2.32
Requires-Dist: rich~=14.0
Requires-Dist: rpyc~=6.0
Requires-Dist: sqlalchemy~=2.0
Requires-Dist: urllib3~=1.26
Requires-Dist: werkzeug~=3.1
Requires-Dist: zxcvbn~=4.4
